funcnodes_pandas/__init__.py
funcnodes_pandas/grouping.py
funcnodes_pandas/utils.py
funcnodes_pandas/dataframe/__init__.py
funcnodes_pandas/dataframe/_autoreader.py
funcnodes_pandas/dataframe/_convert.py
funcnodes_pandas/dataframe/_manipulation.py
funcnodes_pandas/dataframe/_masking.py
funcnodes_pandas/dataframe/_math.py
funcnodes_pandas/dataframe/_rows_cols.py
funcnodes_pandas/dataframe/_types.py
funcnodes_pandas/dataseries/__init__.py
funcnodes_pandas/dataseries/_str.py
funcnodes_pandas-1.0.0.dist-info/METADATA
funcnodes_pandas-1.0.0.dist-info/WHEEL
funcnodes_pandas-1.0.0.dist-info/entry_points.txt
funcnodes_pandas-1.0.0.dist-info/licenses/LICENSE
funcnodes_pandas-1.0.0.dist-info/RECORD
