Metadata-Version: 2.4
Name: funcnodes-pandas
Version: 1.0.0
Summary: pandas nodes for funcnodes
Project-URL: homepage, https://github.com/Linkdlab/funcnodes_pandas
Project-URL: source, https://github.com/Linkdlab/funcnodes_pandas
Project-URL: tracker, https://github.com/Linkdlab/funcnodes_pandas/issues
Project-URL: download, https://pypi.org/project/funcnodes-pandas/#files
Author-email: Julian Kimmig <julian.kimmig@gmx.net>
License: AGPL-3.0
License-File: LICENSE
Classifier: License :: OSI Approved :: GNU Affero General Public License v3 or later (AGPLv3+)
Classifier: Programming Language :: Python :: 3
Requires-Python: >=3.11
Requires-Dist: chardet
Requires-Dist: funcnodes-numpy
Requires-Dist: funcnodes>=1.0.0
Requires-Dist: openpyxl
Requires-Dist: pandas
